submask_cipher.py
submask_cipher-1.0.1.dist-info/LICENSE
submask_cipher-1.0.1.dist-info/METADATA
submask_cipher-1.0.1.dist-info/WHEEL
submask_cipher-1.0.1.dist-info/RECORD
