Metadata-Version: 2.1
Name: submask-cipher
Version: 1.0.1
Summary: Substitution Masking Cipher
License: MIT
Author: Amaan
Author-email: 71920621+amaank404@users.noreply.github.com
Requires-Python: >=3.9,<4.0
Classifier: License :: OSI Approved :: MIT License
Classifier: Programming Language :: Python :: 3
Classifier: Programming Language :: Python :: 3.9
Classifier: Programming Language :: Python :: 3.10
Classifier: Programming Language :: Python :: 3.11
Classifier: Programming Language :: Python :: 3.12
